source_youtube_analytics/__init__.py
source_youtube_analytics/defaults/channel_reports.json
source_youtube_analytics/run.py
source_youtube_analytics/schemas/channel_annotations_a1.json
source_youtube_analytics/schemas/channel_basic_a2.json
source_youtube_analytics/schemas/channel_cards_a1.json
source_youtube_analytics/schemas/channel_combined_a2.json
source_youtube_analytics/schemas/channel_demographics_a1.json
source_youtube_analytics/schemas/channel_device_os_a2.json
source_youtube_analytics/schemas/channel_end_screens_a1.json
source_youtube_analytics/schemas/channel_playback_location_a2.json
source_youtube_analytics/schemas/channel_province_a2.json
source_youtube_analytics/schemas/channel_sharing_service_a1.json
source_youtube_analytics/schemas/channel_subtitles_a2.json
source_youtube_analytics/schemas/channel_traffic_source_a2.json
source_youtube_analytics/schemas/playlist_basic_a1.json
source_youtube_analytics/schemas/playlist_combined_a1.json
source_youtube_analytics/schemas/playlist_device_os_a1.json
source_youtube_analytics/schemas/playlist_playback_location_a1.json
source_youtube_analytics/schemas/playlist_province_a1.json
source_youtube_analytics/schemas/playlist_traffic_source_a1.json
source_youtube_analytics/source.py
source_youtube_analytics/spec.json
airbyte_source_youtube_analytics-0.2.0.dist-info/METADATA
airbyte_source_youtube_analytics-0.2.0.dist-info/WHEEL
airbyte_source_youtube_analytics-0.2.0.dist-info/entry_points.txt
airbyte_source_youtube_analytics-0.2.0.dist-info/RECORD
